lazyfast/__init__.py
lazyfast/cache.py
lazyfast/component.py
lazyfast/context.py
lazyfast/htmx.py
lazyfast/request.py
lazyfast/router.py
lazyfast/script.js
lazyfast/session.py
lazyfast/state.py
lazyfast/tags.py
lazyfast/utils.py
lazyfast-0.1.32.dist-info/LICENSE
lazyfast-0.1.32.dist-info/WHEEL
lazyfast-0.1.32.dist-info/METADATA
lazyfast-0.1.32.dist-info/RECORD
