Metadata-Version: 2.1
Name: lazyfast
Version: 0.1.32
Summary: LazyFast = FastAPI + HTMX + Component-based approach + State management
Home-page: https://github.com/nikirg/lazyfast
Author: Nikita Irgashev
Author-email: nik.irg@yandex.ru
Requires-Python: >=3.11,<4.0
Classifier: Programming Language :: Python :: 3
Classifier: Programming Language :: Python :: 3.11
Requires-Dist: asgiref (>=3.8.1,<4.0.0)
Requires-Dist: fastapi (>=0.115.2,<0.116.0)
Requires-Dist: python-multipart (>=0.0.12,<0.0.13)
Project-URL: Documentation, https://github.com/nikirg/lazyfast/blob/main/DOCS.md
Project-URL: Repository, https://github.com/nikirg/lazyfast
